NewSimpleSQL/SimpleSQL.py
NewSimpleSQL/SimpleSQLite.py
NewSimpleSQL/__init__.py
NewSimpleSQL/serialize_data.py
simple_sqlite/__init__.py
simple_sqlite/simple_lite.py
NewSimpleSQL-0.6.0.9.dist-info/LICENSE
NewSimpleSQL-0.6.0.9.dist-info/METADATA
NewSimpleSQL-0.6.0.9.dist-info/WHEEL
NewSimpleSQL-0.6.0.9.dist-info/top_level.txt
NewSimpleSQL-0.6.0.9.dist-info/RECORD
