Metadata-Version: 2.1
Name: NewSimpleSQL
Version: 0.6.0.9
Summary: This is a library to simplify the use of a SQLite3 database, easy to use, easy to understand.
Home-page: https://github.com/Greem3/NewSimpleSQL
Author: Greem3
Author-email: Greem <ianpichardo575@gmail.com>
Project-URL: GitHub, https://github.com/Greem3/NewSimpleSQL
Classifier: Programming Language :: Python :: 3
Classifier: License :: OSI Approved :: MIT License
Classifier: Operating System :: OS Independent
Requires-Python: >=3.8
License-File: LICENSE
